greencryptopay_py/__init__.py
greencryptopay_py/api.py
greencryptopay_py/exceptions.py
greencryptopay_py/request.py
greencryptopay_py/Handlers/__init__.py
greencryptopay_py/Handlers/standard.py
greencryptopay_py/Handlers/transfer.py
greencryptopay_py/Handlers/utils.py
greencryptopay_py-1.0.0.dist-info/LICENSE
greencryptopay_py-1.0.0.dist-info/METADATA
greencryptopay_py-1.0.0.dist-info/WHEEL
greencryptopay_py-1.0.0.dist-info/top_level.txt
greencryptopay_py-1.0.0.dist-info/RECORD
