Metadata-Version: 2.1
Name: greencryptopay-py
Version: 1.0.0
Summary: This library provides convenient methods for interacting with the Greencryptopay API
Home-page: https://github.com/GreenCryptoPay/greencryptopay_py
Author: greencryptopay
Author-email: support@greencryptopay.com
License: MIT
Platform: UNKNOWN
Classifier: Programming Language :: Python :: 3
Classifier: License :: OSI Approved :: MIT License
Classifier: Operating System :: OS Independent
Requires-Python: >=3.6
License-File: LICENSE
Requires-Dist: requests
